LICENSE.md
README.md
setup.py
porE/__init__.py
porE/version.py
porE.egg-info/PKG-INFO
porE.egg-info/SOURCES.txt
porE.egg-info/dependency_links.txt
porE.egg-info/not-zip-safe
porE.egg-info/requires.txt
porE.egg-info/top_level.txt
porE/gui/__init__.py
porE/gui/pypore.py
porE/hea/HEA.py
porE/hea/__init__.py
porE/io/__init__.py
porE/io/ase2pore.py
porE/lib/__init__.py
porE/lib/porE.f90