Metadata-Version: 2.1
Name: porE
Version: 1.0.7
Summary: Porosity Evaluation tool
Home-page: https://gitlab.com/openmof/porE
Author: Kai Trepte
Author-email: kai.trepte1987@gmail.com
License: APACHE2.0
Platform: UNKNOWN
License-File: LICENSE.md
